CHANGES
LICENSE
MANIFEST.in
Makefile
README
bootstrap.py
buildout.cfg
setup.py
tox.ini
src/admintimestamps/__init__.py
src/admintimestamps/base.py
src/django_admin_timestamps.egg-info/PKG-INFO
src/django_admin_timestamps.egg-info/SOURCES.txt
src/django_admin_timestamps.egg-info/dependency_links.txt
src/django_admin_timestamps.egg-info/not-zip-safe
src/django_admin_timestamps.egg-info/top_level.txt
tests/__init__.py
tests/testproject/__init__.py
tests/testproject/admin.py
tests/testproject/models.py
tests/testproject/settings.py
tests/testproject/tests.py
tests/testproject/urls.py