Metadata-Version: 1.1
Name: django-admin-timestamps
Version: 1.2
Summary: Custom list display of model timestamps for Django Admin.
Home-page: https://bitbucket.org/jaap3/django-admin-timestamps/
Author: Jaap Roes (Eight Media)
Author-email: jaap@eight.nl
License: MIT
Platform: UNKNOWN
Classifier: Development Status :: 5 - Production/Stable
Classifier: Environment :: Web Environment
Classifier: Framework :: Django
Classifier: Intended Audience :: Developers
Classifier: License :: OSI Approved :: MIT License
Classifier: Operating System :: OS Independent
Classifier: Programming Language :: Python :: 2
Classifier: Programming Language :: Python :: 2.6
Classifier: Programming Language :: Python :: 2.7
Classifier: Programming Language :: Python :: 3
Classifier: Programming Language :: Python :: 3.3
Classifier: Programming Language :: Python :: 3.4
